Metadata-Version: 2.1
Name: act4
Version: 3.2.0
Summary: Library for metaprogramming
Home-page: https://github.com/TheArtur128/Act
Download-URL: https://github.com/TheArtur128/Act/archive/refs/tags/v3.2.0.zip
Author: Arthur
Author-email: s9339307190@gmail.com
License: GNU General Public License v3.0
Keywords: monads,library,pipeline,functional-programming,utils,lambda-functions,metaprogramming,annotations,immutability,algebraic-data-types,error-handling,duck-typing,currying,object-proxying,functors,contextualization,utils-library,endofunctors,pseudo-operators,structural-oop
Classifier: Programming Language :: Python :: 3.11
Requires-Python: >=3.11
License-File: LICENSE
Requires-Dist: pyannotating==1.3.0
